setup.py
binterlude/__init__.py
binterlude.egg-info/PKG-INFO
binterlude.egg-info/SOURCES.txt
binterlude.egg-info/dependency_links.txt
binterlude.egg-info/entry_points.txt
binterlude.egg-info/not-zip-safe
binterlude.egg-info/requires.txt
binterlude.egg-info/top_level.txt